README.md
setup.py
bl_db_product_amz_best/__init__.py
bl_db_product_amz_best/database.py
bl_db_product_amz_best/products.py
bl_db_product_amz_best.egg-info/PKG-INFO
bl_db_product_amz_best.egg-info/SOURCES.txt
bl_db_product_amz_best.egg-info/dependency_links.txt
bl_db_product_amz_best.egg-info/requires.txt
bl_db_product_amz_best.egg-info/top_level.txt