Metadata-Version: 2.1
Name: bl-db-product-amz-best
Version: 0.0.3
Summary: bl-db-product-amz-best
Home-page: UNKNOWN
Author-email: rano@bluehack.net
License: UNKNOWN
Keywords: BlueLens,bl-db-product-amz-best
Platform: UNKNOWN
